easymailing_api_client/__init__.py
easymailing_api_client/client.py
easymailing_api_client/errors.py
easymailing_api_client/py.typed
easymailing_api_client/types.py
easymailing_api_client/api/__init__.py
easymailing_api_client/api/account/__init__.py
easymailing_api_client/api/audience/__init__.py
easymailing_api_client/api/audience/get_audience_collection.py
easymailing_api_client/api/audience/get_audience_item.py
easymailing_api_client/api/audience/get_list_segment_item.py
easymailing_api_client/api/audience/get_suscription_form_item.py
easymailing_api_client/api/automation/__init__.py
easymailing_api_client/api/automation/custom_api_trigger_automation_queue_collection.py
easymailing_api_client/api/automation/get_automation_queue_collection.py
easymailing_api_client/api/automation/get_automation_trigger_collection.py
easymailing_api_client/api/campaign/__init__.py
easymailing_api_client/api/campaign/get_automation_queue_item.py
easymailing_api_client/api/campaign/get_automation_trigger_item.py
easymailing_api_client/api/campaign/get_campaign_collection.py
easymailing_api_client/api/campaign/get_campaign_config_item.py
easymailing_api_client/api/campaign/get_campaign_item.py
easymailing_api_client/api/campaign/get_campaign_send_stat_item.py
easymailing_api_client/api/campaign/get_consent_item.py
easymailing_api_client/api/campaign/get_email_config_item.py
easymailing_api_client/api/campaign/post_campaign_collection.py
easymailing_api_client/api/campaign/put_campaign_item.py
easymailing_api_client/api/campaign/schedule_campaign_item.py
easymailing_api_client/api/campaign/send_now_campaign_item.py
easymailing_api_client/api/configuration/__init__.py
easymailing_api_client/api/configuration/delete_data_manager_item.py
easymailing_api_client/api/configuration/delete_sender_item.py
easymailing_api_client/api/configuration/delete_treatment_purpose_item.py
easymailing_api_client/api/configuration/get_data_manager_collection.py
easymailing_client-0.1.0.dist-info/WHEEL
easymailing_client-0.1.0.dist-info/METADATA
easymailing_client-0.1.0.dist-info/RECORD
