Metadata-Version: 2.1
Name: easymailing-client
Version: 0.1.0
Summary: A client library for accessing Easymailing API
Author-email: Juan Luis Cano Rodríguez <hello@juanlu.space>
Requires-Dist: httpx >=0.15.4,<0.25.0
Requires-Dist: attrs >=21.3.0
Requires-Dist: python-dateutil ~=2.8.0
